timey/__init__.py
timey/timey.py
timey-1.1.1.dist-info/LICENSE
timey-1.1.1.dist-info/METADATA
timey-1.1.1.dist-info/WHEEL
timey-1.1.1.dist-info/entry_points.txt
timey-1.1.1.dist-info/top_level.txt
timey-1.1.1.dist-info/RECORD
