Metadata-Version: 2.1
Name: timey
Version: 1.1.1
Summary: CLI timer app to keep track of your life
Home-page: https://github.com/haranrk/
Author: Haran Rajkumar
Author-email: haranrajkumar97@gmail.com
License: UNKNOWN
Platform: UNKNOWN
Classifier: Programming Language :: Python :: 3
Classifier: License :: OSI Approved :: MIT License
Classifier: Operating System :: OS Independent
Requires-Dist: click
